{
  "animationsystem.dll": {
    "AnimationSystemUtils_001": 8462736,
    "AnimationSystem_001": 8429744
  },
  "client.dll": {
    "ClientToolsInfo_001": 33882560,
    "EmptyWorldService001_Client": 33634960,
    "GameClientExports001": 33869408,
    "LegacyGameUI001": 33981920,
    "Source2Client002": 36859792,
    "Source2ClientConfig001": 36278224,
    "Source2ClientPrediction001": 33912368,
    "Source2ClientUI001": 33975104
  },
  "engine2.dll": {
    "BenchmarkService001": 6367568,
    "BugService001": 9218304,
    "ClientServerEngineLoopService_001": 9486336,
    "ClientServerSharedHandleSystem001": 9483696,
    "EngineGameUI001": 6357664,
    "EngineServiceMgr001": 9484512,
    "GameEventSystemClientV001": 9485248,
    "GameEventSystemServerV001": 9485552,
    "GameResourceServiceClientV001": 6367824,
    "GameResourceServiceServerV001": 6367920,
    "GameUIService_001": 9219376,
    "HostStateMgr001": 6369936,
    "INETSUPPORT_001": 6340672,
    "InputService_001": 9220128,
    "KeyValueCache001": 6370112,
    "MapListService_001": 9477776,
    "NetworkClientService_001": 9478176,
    "NetworkP2PService_001": 9479008,
    "NetworkServerService_001": 9479440,
    "NetworkService_001": 6368288,
    "RenderService_001": 9480064,
    "ScreenshotService001": 9480768,
    "SimpleEngineLoopService_001": 6370208,
    "SoundService_001": 6368352,
    "Source2EngineToClient001": 6355872,
    "Source2EngineToClientStringTable001": 6355968,
    "Source2EngineToServer001": 6356088,
    "Source2EngineToServerStringTable001": 6356128,
    "SplitScreenService_001": 6369088,
    "StatsService_001": 9481728,
    "ToolService_001": 6369536,
    "VENGINE_GAMEUIFUNCS_VERSION005": 6357808,
    "VProfService_001": 6369600
  },
  "filesystem_stdio.dll": {
    "VAsyncFileSystem2_001": 2185696,
    "VFileSystem017": 2185120
  },
  "host.dll": {
    "DebugDrawQueueManager001": 1282144,
    "GameModelInfo001": 1282208,
    "GameSystem2HostHook": 1282272,
    "HostUtils001": 1346224,
    "PredictionDiffManager001": 1282544,
    "SaveRestoreDataVersion001": 1282848,
    "SinglePlayerSharedMemory001": 1282896,
    "Source2Host001": 1283008
  },
  "imemanager.dll": {
    "IMEManager001": 224032
  },
  "inputsystem.dll": {
    "InputStackSystemVersion001": 265776,
    "InputSystemVersion001": 273232
  },
  "localize.dll": {
    "Localize_001": 401792
  },
  "matchmaking.dll": {
    "GameTypes001": 1773440,
    "MATCHFRAMEWORK_001": 1806432
  },
  "materialsystem2.dll": {
    "FontManager_001": 1433184,
    "MaterialUtils_001": 1334592,
    "PostProcessingSystem_001": 1334352,
    "TextLayout_001": 1334480,
    "VMaterialSystem2_001": 1431376
  },
  "meshsystem.dll": {
    "MeshSystem001": 1379360
  },
  "navsystem.dll": {
    "NavSystem001": 1190192
  },
  "networksystem.dll": {
    "FlattenedSerializersVersion001": 2545408,
    "NetworkMessagesVersion001": 2709968,
    "NetworkSystemVersion001": 2649680,
    "SerializedEntitiesVersion001": 2649920
  },
  "panorama.dll": {
    "PanoramaUIEngine001": 5270832
  },
  "panorama_text_pango.dll": {
    "PanoramaTextServices001": 2853440
  },
  "panoramauiclient.dll": {
    "PanoramaUIClient001": 2712608
  },
  "particles.dll": {
    "ParticleSystemMgr003": 5546944
  },
  "pulse_system.dll": {
    "IPulseSystem_001": 2045600
  },
  "rendersystemdx11.dll": {
    "RenderDeviceMgr001": 4371760,
    "RenderUtils_001": 4374056,
    "VRenderDeviceMgrBackdoor001": 4371920
  },
  "resourcesystem.dll": {
    "ResourceSystem013": 537056
  },
  "scenefilecache.dll": {
    "ResponseRulesCache001": 1005808,
    "SceneFileCache002": 1006200
  },
  "scenesystem.dll": {
    "RenderingPipelines_001": 6699936,
    "SceneSystem_002": 9286800,
    "SceneUtils_001": 6703792
  },
  "schemasystem.dll": {
    "SchemaSystem_001": 485376
  },
  "server.dll": {
    "EmptyWorldService001_Server": 29293872,
    "EntitySubclassUtilsV001": 28947376,
    "NavGameTest001": 29999568,
    "ServerToolsInfo_001": 29659576,
    "Source2GameClients001": 29654032,
    "Source2GameDirector001": 31332336,
    "Source2GameEntities001": 29657280,
    "Source2Server001": 29656848,
    "Source2ServerConfig001": 32500376,
    "customnavsystem001": 28821144
  },
  "soundsystem.dll": {
    "SoundOpSystem001": 5319104,
    "SoundOpSystemEdit001": 5318784,
    "SoundSystem001": 5317472,
    "VMixEditTool001": 93620159
  },
  "steamaudio.dll": {
    "SteamAudio001": 2483744
  },
  "steamclient64.dll": {
    "IVALIDATE001": 23842968,
    "SteamClient006": 23831808,
    "SteamClient007": 23831816,
    "SteamClient008": 23831824,
    "SteamClient009": 23831832,
    "SteamClient010": 23831840,
    "SteamClient011": 23831848,
    "SteamClient012": 23831856,
    "SteamClient013": 23831864,
    "SteamClient014": 23831872,
    "SteamClient015": 23831880,
    "SteamClient016": 23831888,
    "SteamClient017": 23831896,
    "SteamClient018": 23831904,
    "SteamClient019": 23831912,
    "SteamClient020": 23831920,
    "SteamClient021": 23831928,
    "SteamClient022": 23831936,
    "SteamClient023": 23831944,
    "p2pvoice002": 21914239,
    "p2pvoicesingleton002": 23679216
  },
  "tier0.dll": {
    "TestScriptMgr001": 3794672,
    "VEngineCvar007": 3838896,
    "VProcessUtils002": 3794576,
    "VStringTokenSystem001": 3997872
  },
  "v8system.dll": {
    "Source2V8System001": 202544
  },
  "vphysics2.dll": {
    "VPhysics2_Interface_001": 4251040
  },
  "vscript.dll": {
    "VScriptManager010": 1291280
  },
  "vstdlib_s64.dll": {
    "IVALIDATE001": 457104,
    "VEngineCvar002": 450672
  },
  "worldrenderer.dll": {
    "WorldRendererMgr001": 2251840
  }
}